aviatrix_migration-0.2.148.data/data/migration/discovery_migration/aws/generic/versions.tf
aviatrix_migration-0.2.148.data/data/migration/discovery_migration/aws/generic/main-rtb-associations.tf
aviatrix_migration-0.2.148.data/data/migration/discovery_migration/aws/generic/account.template
aviatrix_migration-0.2.148.data/data/migration/discovery_migration/aws/generic/terraform-import-associations.sh
aviatrix_migration-0.2.148.data/data/migration/discovery_migration/aws/generic/terraform.tfvars
aviatrix_migration-0.2.148.data/data/migration/discovery_migration/aws/generic/subnet-associations.tf
aviatrix_migration-0.2.148.data/data/migration/discovery_migration/aws/generic/vpc_id.tf
aviatrix_migration-0.2.148.data/data/migration/discovery_migration/aws/generic/providers.tf
aviatrix_migration-0.2.148.data/data/migration/discovery_migration/aws/generic/main.tf
aviatrix_migration-0.2.148.data/data/migration/discovery_migration/aws/generic/variables.tf
aviatrix_migration-0.2.148.data/data/migration/discovery_migration/aws/generic/module_aws_brownfield_spoke_vpc/versions.tf
aviatrix_migration-0.2.148.data/data/migration/discovery_migration/aws/generic/module_aws_brownfield_spoke_vpc/variables.tf
aviatrix_migration-0.2.148.data/data/migration/discovery_migration/aws/generic/module_aws_brownfield_spoke_vpc/main-vpc-name.tf
aviatrix_migration-0.2.148.data/data/migration/discovery_migration/aws/combined/dmhelp.sh
aviatrix_migration-0.2.148.data/data/migration/discovery_migration/aws/combined/versions.tf
aviatrix_migration-0.2.148.data/data/migration/discovery_migration/aws/combined/main-rtb-associations.tf
aviatrix_migration-0.2.148.data/data/migration/discovery_migration/aws/combined/account.template
aviatrix_migration-0.2.148.data/data/migration/discovery_migration/aws/combined/terraform-import-associations.sh
aviatrix_migration-0.2.148.data/data/migration/discovery_migration/aws/combined/terraform.tfvars
aviatrix_migration-0.2.148.dist-info/WHEEL
aviatrix_migration-0.2.148.dist-info/top_level.txt
aviatrix_migration-0.2.148.dist-info/entry_points.txt
aviatrix_migration-0.2.148.dist-info/RECORD
aviatrix_migration-0.2.148.dist-info/METADATA
