Metadata-Version: 2.1
Name: aviatrix-migration
Version: 0.2.148
Summary: Aviatrix Discovery Migration
Author: Aviatrix Automation
Author-email: aviatrix-ps-dev@aviatrix.com
Project-URL: Changelog, https://github.com/aviatrix-automation/discovery_migration/blob/master/CHANGELOG.rst
Project-URL: Issue Tracker, https://github.com/aviatrix-automation/discovery_migration/issues
Classifier: Development Status :: 4 - Beta
Classifier: Environment :: Console
Classifier: Intended Audience :: Developers
Classifier: Operating System :: POSIX
Classifier: Programming Language :: Python
Classifier: Programming Language :: Python :: 3
Classifier: Programming Language :: Python :: 3 :: Only
Classifier: Programming Language :: Python :: 3.7
Classifier: Programming Language :: Python :: 3.8
Classifier: Programming Language :: Python :: 3.9
Classifier: Programming Language :: Python :: Implementation :: CPython
Classifier: Topic :: Utilities
Requires-Python: >=3.7
Requires-Dist: boto3==1.24.22
Requires-Dist: botocore==1.27.22
Requires-Dist: certifi==2020.12.5
Requires-Dist: chardet==4.0.0
Requires-Dist: decorator==5.0.9
Requires-Dist: idna==2.10
Requires-Dist: Jinja2==3.0.3
Requires-Dist: jmespath==0.10.0
Requires-Dist: py==1.10.0
Requires-Dist: pydantic==1.9.0
Requires-Dist: python-dateutil==2.8.1
Requires-Dist: PyYAML==6.0.2
Requires-Dist: requests==2.25.1
Requires-Dist: retry==0.9.2
Requires-Dist: s3transfer==0.6.0
Requires-Dist: six==1.16.0
Requires-Dist: typing-extensions==4.5.0
Requires-Dist: urllib3==1.26.4
Requires-Dist: packaging==21.3
Requires-Dist: python-hcl2==4.3.2
Requires-Dist: aviatrix-migration-nat
Requires-Dist: azure-applicationinsights==0.1.0
Requires-Dist: azure-batch==4.1.3
Requires-Dist: azure-common==1.1.23
Requires-Dist: azure-core==1.29.1
Requires-Dist: azure-cosmosdb-nspkg==2.0.2
Requires-Dist: azure-cosmosdb-table==1.0.6
Requires-Dist: azure-datalake-store==0.0.48
Requires-Dist: azure-eventgrid==1.3.0
Requires-Dist: azure-graphrbac==0.40.0
Requires-Dist: azure-identity>=1.5.0
Requires-Dist: azure-keyvault==1.1.0
Requires-Dist: azure-loganalytics==0.1.0
Requires-Dist: azure-mgmt-advisor==1.0.1
Requires-Dist: azure-mgmt-applicationinsights==0.1.1
Requires-Dist: azure-mgmt-authorization==0.50.0
Requires-Dist: azure-mgmt-batch==5.0.1
Requires-Dist: azure-mgmt-batchai==2.0.0
Requires-Dist: azure-mgmt-billing==0.2.0
Requires-Dist: azure-mgmt-cdn==3.1.0
Requires-Dist: azure-mgmt-cognitiveservices==3.0.0
Requires-Dist: azure-mgmt-commerce==1.0.1
Requires-Dist: azure-mgmt-compute==4.6.2
Requires-Dist: azure-mgmt-consumption==2.0.0
Requires-Dist: azure-mgmt-containerinstance==1.5.0
Requires-Dist: azure-mgmt-containerregistry==2.8.0
Requires-Dist: azure-mgmt-containerservice==4.4.0
Requires-Dist: azure-mgmt-cosmosdb==0.4.1
Requires-Dist: azure-mgmt-datafactory==0.6.0
Requires-Dist: azure-mgmt-datalake-analytics==0.6.0
Requires-Dist: azure-mgmt-datalake-nspkg==3.0.1
Requires-Dist: azure-mgmt-datalake-store==0.5.0
Requires-Dist: azure-mgmt-datamigration==1.0.0
Requires-Dist: azure-mgmt-devspaces==0.1.0
Requires-Dist: azure-mgmt-devtestlabs==2.2.0
Requires-Dist: azure-mgmt-dns==2.1.0
Requires-Dist: azure-mgmt-eventgrid==1.0.0
Requires-Dist: azure-mgmt-eventhub==2.6.0
Requires-Dist: azure-mgmt-hanaonazure==0.1.1
Requires-Dist: azure-mgmt-iotcentral==0.1.0
Requires-Dist: azure-mgmt-iothub==0.5.0
Requires-Dist: azure-mgmt-iothubprovisioningservices==0.2.0
Requires-Dist: azure-mgmt-keyvault==1.1.0
Requires-Dist: azure-mgmt-loganalytics==0.2.0
Requires-Dist: azure-mgmt-logic==3.0.0
Requires-Dist: azure-mgmt-machinelearningcompute==0.4.1
Requires-Dist: azure-mgmt-managementgroups==0.1.0
Requires-Dist: azure-mgmt-managementpartner==0.1.1
Requires-Dist: azure-mgmt-maps==0.1.0
Requires-Dist: azure-mgmt-marketplaceordering==0.1.0
Requires-Dist: azure-mgmt-media==1.0.0
Requires-Dist: azure-mgmt-monitor==0.5.2
Requires-Dist: azure-mgmt-msi==0.2.0
Requires-Dist: azure-mgmt-network==20.0.0
Requires-Dist: azure-mgmt-notificationhubs==2.1.0
Requires-Dist: azure-mgmt-nspkg==3.0.2
Requires-Dist: azure-mgmt-policyinsights==0.1.0
Requires-Dist: azure-mgmt-powerbiembedded==2.0.0
Requires-Dist: azure-mgmt-rdbms==1.9.0
Requires-Dist: azure-mgmt-recoveryservices==0.3.0
Requires-Dist: azure-mgmt-recoveryservicesbackup==0.3.0
Requires-Dist: azure-mgmt-redis==5.0.0
Requires-Dist: azure-mgmt-relay==0.1.0
Requires-Dist: azure-mgmt-reservations==1.0.0
Requires-Dist: azure-mgmt-resource==2.2.0
Requires-Dist: azure-mgmt-resourcegraph==8.0.0
Requires-Dist: azure-mgmt-scheduler==2.0.0
Requires-Dist: azure-mgmt-search==2.1.0
Requires-Dist: azure-mgmt-servicebus==0.5.3
Requires-Dist: azure-mgmt-servicefabric==0.2.0
Requires-Dist: azure-mgmt-signalr==0.1.1
Requires-Dist: azure-mgmt-sql==0.9.1
Requires-Dist: azure-mgmt-storage==2.0.0
Requires-Dist: azure-mgmt-subscription==0.2.0
Requires-Dist: azure-mgmt-trafficmanager==0.50.0
Requires-Dist: azure-mgmt-web==0.35.0
Requires-Dist: azure-nspkg==3.0.2
Requires-Dist: azure-servicebus==0.21.1
Requires-Dist: azure-servicefabric==6.3.0.0
Requires-Dist: azure-servicemanagement-legacy==0.20.6
Requires-Dist: azure-storage-blob==1.5.0
Requires-Dist: azure-storage-common==1.4.2
Requires-Dist: azure-storage-file==1.4.0
Requires-Dist: azure-storage-queue==1.4.0
